cdnetworks/__init__.py
cdnetworks/service.py
cdnetworks/services/__init__.py
cdnetworks/services/cdns.py
cdnetworks-0.3.1.dist-info/LICENSE
cdnetworks-0.3.1.dist-info/METADATA
cdnetworks-0.3.1.dist-info/WHEEL
cdnetworks-0.3.1.dist-info/top_level.txt
cdnetworks-0.3.1.dist-info/RECORD
